teatime/__init__.py
teatime/utils.py
teatime/plugins/__init__.py
teatime/plugins/base.py
teatime/plugins/context.py
teatime/plugins/eth1/__init__.py
teatime/plugins/eth1/account_creation.py
teatime/plugins/eth1/account_import.py
teatime/plugins/eth1/gas_limits.py
teatime/plugins/eth1/information_leaks.py
teatime/plugins/eth1/manipulation.py
teatime/plugins/eth1/mining.py
teatime/plugins/eth1/network.py
teatime/plugins/eth1/open_accounts.py
teatime/plugins/eth1/rpc.py
teatime/plugins/eth1/sha3.py
teatime/plugins/eth1/sync.py
teatime/plugins/eth1/tx_limits.py
teatime/plugins/eth1/txpool.py
teatime/plugins/eth1/upgrade.py
teatime/plugins/eth1/version.py
teatime/plugins/eth1/websocket.py
teatime/plugins/ipfs/__init__.py
teatime/plugins/ipfs/add.py
teatime/plugins/ipfs/commands.py
teatime/plugins/ipfs/files.py
teatime/plugins/ipfs/keys.py
teatime/plugins/ipfs/logs.py
teatime/plugins/ipfs/p2p.py
teatime/plugins/ipfs/pins.py
teatime/plugins/ipfs/shutdown.py
teatime/plugins/ipfs/version.py
teatime/plugins/ipfs/webui.py
teatime/reporting/__init__.py
teatime/reporting/issue.py
teatime/reporting/report.py
teatime/scanner/__init__.py
teatime/scanner/scanner.py
tests/plugins/__init__.py
tests/plugins/eth1/__init__.py
tests/plugins/eth1/test_plugin_format.py
tests/plugins/eth1/test_plugins.py
tests/plugins/eth1/util.py
tests/plugins/ipfs/__init__.py
tests/plugins/ipfs/test_plugin_format.py
tests/plugins/ipfs/test_plugins.py
teatime-0.3.1.dist-info/AUTHORS.rst
teatime-0.3.1.dist-info/LICENSE
teatime-0.3.1.dist-info/METADATA
teatime-0.3.1.dist-info/WHEEL
teatime-0.3.1.dist-info/top_level.txt
teatime-0.3.1.dist-info/RECORD
