Metadata-Version: 2.1
Name: teatime
Version: 0.3.1
Summary: Just deployed a blockchain node? Have some tea.
Home-page: https://github.com/dmuhs/teatime
Author: Dominik Muhs
Author-email: dmuhs@protonmail.ch
License: MIT license
Keywords: teatime
Platform: UNKNOWN
Classifier: Development Status :: 4 - Beta
Classifier: License :: OSI Approved :: MIT License
Classifier: Natural Language :: English
Classifier: Intended Audience :: Developers
Classifier: Intended Audience :: Education
Classifier: Intended Audience :: Information Technology
Classifier: Topic :: Security
Classifier: Topic :: Software Development :: Libraries :: Python Modules
Classifier: Topic :: Software Development :: Quality Assurance
Classifier: Topic :: Utilities
Classifier: Typing :: Typed
Classifier: Programming Language :: Python :: 3
Classifier: Programming Language :: Python :: 3.6
Classifier: Programming Language :: Python :: 3.7
Classifier: Programming Language :: Python :: 3.8
Classifier: Programming Language :: Python :: Implementation :: PyPy
Requires-Python: >=3.6
Requires-Dist: requests (==2.25.1)
Requires-Dist: loguru (==0.5.3)
